{
  "openapi": "3.0.1",
  "info": {
    "title": "CriptoBiyuya",
    "version": "1.0"
  },
  "paths": {
    "/api/Client": {
      "get": {
        "tags": [
          "Client"
        ],
        "responses": {
          "200": {
            "description": "OK",
            "content": {
              "text/plain": {
                "schema": {
                  "type": "array",
                  "items": {
                    "$ref": "#/components/schemas/ClientDTO"
                  }
                }
              },
              "application/json": {
                "schema": {
                  "type": "array",
                  "items": {
                    "$ref": "#/components/schemas/ClientDTO"
                  }
                }
              },
              "text/json": {
                "schema": {
                  "type": "array",
                  "items": {
                    "$ref": "#/components/schemas/ClientDTO"
                  }
                }
              }
            }
          }
        }
      },
      "post": {
        "tags": [
          "Client"
        ],
        "requestBody": {
          "content": {
            "application/json": {
              "schema": {
                "$ref": "#/components/schemas/ClientDTO"
              }
            },
            "text/json": {
              "schema": {
                "$ref": "#/components/schemas/ClientDTO"
              }
            },
            "application/*+json": {
              "schema": {
                "$ref": "#/components/schemas/ClientDTO"
              }
            }
          }
        },
        "responses": {
          "200": {
            "description": "OK",
            "content": {
              "text/plain": {
                "schema": {
                  "$ref": "#/components/schemas/ClientDTO"
                }
              },
              "application/json": {
                "schema": {
                  "$ref": "#/components/schemas/ClientDTO"
                }
              },
              "text/json": {
                "schema": {
                  "$ref": "#/components/schemas/ClientDTO"
                }
              }
            }
          }
        }
      }
    },
    "/api/Client/{id}": {
      "get": {
        "tags": [
          "Client"
        ],
        "parameters": [
          {
            "name": "id",
            "in": "path",
            "required": true,
            "schema": {
              "type": "integer",
              "format": "int32"
            }
          }
        ],
        "responses": {
          "200": {
            "description": "OK",
            "content": {
              "text/plain": {
                "schema": {
                  "$ref": "#/components/schemas/ClientDTO"
                }
              },
              "application/json": {
                "schema": {
                  "$ref": "#/components/schemas/ClientDTO"
                }
              },
              "text/json": {
                "schema": {
                  "$ref": "#/components/schemas/ClientDTO"
                }
              }
            }
          }
        }
      },
      "delete": {
        "tags": [
          "Client"
        ],
        "parameters": [
          {
            "name": "id",
            "in": "path",
            "required": true,
            "schema": {
              "type": "integer",
              "format": "int32"
            }
          }
        ],
        "responses": {
          "200": {
            "description": "OK"
          }
        }
      }
    },
    "/api/Transaction": {
      "get": {
        "tags": [
          "Transaction"
        ],
        "responses": {
          "200": {
            "description": "OK",
            "content": {
              "text/plain": {
                "schema": {
                  "type": "array",
                  "items": {
                    "$ref": "#/components/schemas/Transaction"
                  }
                }
              },
              "application/json": {
                "schema": {
                  "type": "array",
                  "items": {
                    "$ref": "#/components/schemas/Transaction"
                  }
                }
              },
              "text/json": {
                "schema": {
                  "type": "array",
                  "items": {
                    "$ref": "#/components/schemas/Transaction"
                  }
                }
              }
            }
          }
        }
      },
      "post": {
        "tags": [
          "Transaction"
        ],
        "requestBody": {
          "content": {
            "application/json": {
              "schema": {
                "$ref": "#/components/schemas/TransactionDTO"
              }
            },
            "text/json": {
              "schema": {
                "$ref": "#/components/schemas/TransactionDTO"
              }
            },
            "application/*+json": {
              "schema": {
                "$ref": "#/components/schemas/TransactionDTO"
              }
            }
          }
        },
        "responses": {
          "200": {
            "description": "OK"
          }
        }
      }
    },
    "/api/Transaction/by-client/{clientId}": {
      "get": {
        "tags": [
          "Transaction"
        ],
        "parameters": [
          {
            "name": "clientId",
            "in": "path",
            "required": true,
            "schema": {
              "type": "integer",
              "format": "int32"
            }
          }
        ],
        "responses": {
          "200": {
            "description": "OK",
            "content": {
              "text/plain": {
                "schema": {
                  "type": "array",
                  "items": {
                    "$ref": "#/components/schemas/Transaction"
                  }
                }
              },
              "application/json": {
                "schema": {
                  "type": "array",
                  "items": {
                    "$ref": "#/components/schemas/Transaction"
                  }
                }
              },
              "text/json": {
                "schema": {
                  "type": "array",
                  "items": {
                    "$ref": "#/components/schemas/Transaction"
                  }
                }
              }
            }
          }
        }
      }
    },
    "/api/Transaction/{id}": {
      "get": {
        "tags": [
          "Transaction"
        ],
        "parameters": [
          {
            "name": "id",
            "in": "path",
            "required": true,
            "schema": {
              "type": "integer",
              "format": "int32"
            }
          }
        ],
        "responses": {
          "200": {
            "description": "OK",
            "content": {
              "text/plain": {
                "schema": {
                  "$ref": "#/components/schemas/Transaction"
                }
              },
              "application/json": {
                "schema": {
                  "$ref": "#/components/schemas/Transaction"
                }
              },
              "text/json": {
                "schema": {
                  "$ref": "#/components/schemas/Transaction"
                }
              }
            }
          }
        }
      },
      "put": {
        "tags": [
          "Transaction"
        ],
        "parameters": [
          {
            "name": "id",
            "in": "path",
            "required": true,
            "schema": {
              "type": "integer",
              "format": "int32"
            }
          }
        ],
        "requestBody": {
          "content": {
            "application/json": {
              "schema": {
                "$ref": "#/components/schemas/TransactionDTO"
              }
            },
            "text/json": {
              "schema": {
                "$ref": "#/components/schemas/TransactionDTO"
              }
            },
            "application/*+json": {
              "schema": {
                "$ref": "#/components/schemas/TransactionDTO"
              }
            }
          }
        },
        "responses": {
          "200": {
            "description": "OK"
          }
        }
      },
      "delete": {
        "tags": [
          "Transaction"
        ],
        "parameters": [
          {
            "name": "id",
            "in": "path",
            "required": true,
            "schema": {
              "type": "integer",
              "format": "int32"
            }
          }
        ],
        "responses": {
          "200": {
            "description": "OK"
          }
        }
      }
    },
    "/WeatherForecast": {
      "get": {
        "tags": [
          "WeatherForecast"
        ],
        "operationId": "GetWeatherForecast",
        "responses": {
          "200": {
            "description": "OK",
            "content": {
              "text/plain": {
                "schema": {
                  "type": "array",
                  "items": {
                    "$ref": "#/components/schemas/WeatherForecast"
                  }
                }
              },
              "application/json": {
                "schema": {
                  "type": "array",
                  "items": {
                    "$ref": "#/components/schemas/WeatherForecast"
                  }
                }
              },
              "text/json": {
                "schema": {
                  "type": "array",
                  "items": {
                    "$ref": "#/components/schemas/WeatherForecast"
                  }
                }
              }
            }
          }
        }
      }
    }
  },
  "components": {
    "schemas": {
      "Client": {
        "required": [
          "email",
          "name"
        ],
        "type": "object",
        "properties": {
          "id": {
            "type": "integer",
            "format": "int32"
          },
          "name": {
            "minLength": 1,
            "type": "string"
          },
          "email": {
            "minLength": 1,
            "type": "string"
          },
          "transactions": {
            "type": "array",
            "items": {
              "$ref": "#/components/schemas/Transaction"
            },
            "nullable": true
          }
        },
        "additionalProperties": false
      },
      "ClientDTO": {
        "required": [
          "email",
          "name"
        ],
        "type": "object",
        "properties": {
          "id": {
            "type": "integer",
            "format": "int32"
          },
          "name": {
            "minLength": 1,
            "type": "string"
          },
          "email": {
            "minLength": 1,
            "type": "string",
            "format": "email"
          },
          "transactions": {
            "type": "array",
            "items": {
              "$ref": "#/components/schemas/TransactionDTO"
            },
            "nullable": true
          }
        },
        "additionalProperties": false
      },
      "Transaction": {
        "required": [
          "action",
          "crypto_amount",
          "crypto_code",
          "datetime",
          "money"
        ],
        "type": "object",
        "properties": {
          "id": {
            "type": "integer",
            "format": "int32"
          },
          "crypto_code": {
            "minLength": 1,
            "type": "string"
          },
          "action": {
            "minLength": 1,
            "type": "string"
          },
          "crypto_amount": {
            "type": "number",
            "format": "double"
          },
          "money": {
            "type": "number",
            "format": "double"
          },
          "datetime": {
            "type": "string",
            "format": "date-time"
          },
          "client_id": {
            "type": "integer",
            "format": "int32"
          },
          "client": {
            "$ref": "#/components/schemas/Client"
          }
        },
        "additionalProperties": false
      },
      "TransactionDTO": {
        "required": [
          "action",
          "client_id",
          "crypto_amount",
          "crypto_code",
          "datetime"
        ],
        "type": "object",
        "properties": {
          "id": {
            "type": "integer",
            "format": "int32"
          },
          "crypto_code": {
            "minLength": 1,
            "type": "string"
          },
          "action": {
            "minLength": 1,
            "type": "string"
          },
          "crypto_amount": {
            "type": "number",
            "format": "double"
          },
          "money": {
            "type": "number",
            "format": "double"
          },
          "datetime": {
            "type": "string",
            "format": "date-time"
          },
          "client_id": {
            "type": "integer",
            "format": "int32"
          }
        },
        "additionalProperties": false
      },
      "WeatherForecast": {
        "type": "object",
        "properties": {
          "date": {
            "type": "string",
            "format": "date"
          },
          "temperatureC": {
            "type": "integer",
            "format": "int32"
          },
          "temperatureF": {
            "type": "integer",
            "format": "int32",
            "readOnly": true
          },
          "summary": {
            "type": "string",
            "nullable": true
          }
        },
        "additionalProperties": false
      }
    }
  }
}